{"PMT_Baseline_bins": [2500, 4000, 400]       , "PMT_BaselineRMS_bins": [0.0, 20.0, 100]            , "PMT_nSensors_bins": [-0.5, 12.5, 13]    , "SiPM_Baseline_bins": [200, 800.0, 100]        , "SiPM_BaselineRMS_bins": [0.0, 10.0, 100]             , "SiPM_nSensors_bins": [1750.5, 1800.5, 50] , "PMTs_AdamPlot_bins": [1000, 4096, 100],
 "PMT_Baseline_labels": ["PMT Baseline (ADC)"], "PMT_BaselineRMS_labels": ["PMT Baseline RMS (ADC)"], "PMT_nSensors_labels": ["Number of PMTs"], "SiPM_Baseline_labels": ["SiPM Baseline (ADC)"], "SiPM_BaselineRMS_labels": ["SiPM Baseline RMS (ADC)"], "SiPM_nSensors_labels": ["Number of SiPMs"], "PMTs_AdamPlot_labels": [""],
 "PMT_Baseline_scales": ["linear"]            , "PMT_BaselineRMS_scales": ["linear"]                , "PMT_nSensors_scales": ["linear"]        , "SiPM_Baseline_scales": ["linear"]             , "SiPM_BaselineRMS_scales": ["linear"]                 , "SiPM_nSensors_scales": ["linear"]         , "PMTs_AdamPlot_scales": ["log"],
 "n_baseline": 48000, "n_PMTs": 12}
